waffle_dough/__init__.py
waffle_dough/cli.py
waffle_dough/config.py
waffle_dough/database/__init__.py
waffle_dough/database/engine.py
waffle_dough/database/service.py
waffle_dough/database/model/__init__.py
waffle_dough/database/model/annotation.py
waffle_dough/database/model/base.py
waffle_dough/database/model/category.py
waffle_dough/database/model/image.py
waffle_dough/database/repository/__init__.py
waffle_dough/database/repository/annotation_repository.py
waffle_dough/database/repository/base_repository.py
waffle_dough/database/repository/category_repository.py
waffle_dough/database/repository/image_repository.py
waffle_dough/dataset/__init__.py
waffle_dough/dataset/dataset.py
waffle_dough/dataset/adapter/__init__.py
waffle_dough/dataset/adapter/base_adapter.py
waffle_dough/dataset/adapter/coco_adapter.py
waffle_dough/dataset/adapter/state.py
waffle_dough/dataset/adapter/yolo_adapter.py
waffle_dough/dataset/adapter/callback/__init__.py
waffle_dough/dataset/adapter/callback/adapter_callback.py
waffle_dough/dataset/adapter/callback/progress/__init__.py
waffle_dough/dataset/adapter/callback/progress/file.py
waffle_dough/dataset/adapter/callback/progress/progress.py
waffle_dough/dataset/adapter/callback/progress/tqdm.py
waffle_dough/dataset/util/__init__.py
waffle_dough/dataset/util/iterator.py
waffle_dough/dataset/util/visualize.py
waffle_dough/exception/__init__.py
waffle_dough/exception/base_exception.py
waffle_dough/exception/database_exception.py
waffle_dough/exception/dataset_exception.py
waffle_dough/exception/field_exception.py
waffle_dough/field/__init__.py
waffle_dough/field/annotation_info.py
waffle_dough/field/base_field.py
waffle_dough/field/category_info.py
waffle_dough/field/image_info.py
waffle_dough/field/validator/__init__.py
waffle_dough/field/validator/annotation_validator.py
waffle_dough/field/validator/category_validator.py
waffle_dough/field/validator/image_validator.py
waffle_dough/image/__init__.py
waffle_dough/image/io.py
waffle_dough-0.0.0.dist-info/LICENSE
waffle_dough-0.0.0.dist-info/METADATA
waffle_dough-0.0.0.dist-info/WHEEL
waffle_dough-0.0.0.dist-info/entry_points.txt
waffle_dough-0.0.0.dist-info/top_level.txt
waffle_dough-0.0.0.dist-info/RECORD
